fastmcp_mysql/__init__.py
fastmcp_mysql/__main__.py
fastmcp_mysql/config.py
fastmcp_mysql/connection.py
fastmcp_mysql/monitoring.py
fastmcp_mysql/server.py
fastmcp_mysql/server_enhanced.py
fastmcp_mysql/cache/__init__.py
fastmcp_mysql/cache/interfaces.py
fastmcp_mysql/cache/invalidator.py
fastmcp_mysql/cache/lru_cache.py
fastmcp_mysql/cache/manager.py
fastmcp_mysql/cache/ttl_cache.py
fastmcp_mysql/observability/__init__.py
fastmcp_mysql/observability/health.py
fastmcp_mysql/observability/logging.py
fastmcp_mysql/observability/metrics.py
fastmcp_mysql/observability/tracing.py
fastmcp_mysql/security/__init__.py
fastmcp_mysql/security/config.py
fastmcp_mysql/security/exceptions.py
fastmcp_mysql/security/manager.py
fastmcp_mysql/security/filtering/__init__.py
fastmcp_mysql/security/filtering/blacklist.py
fastmcp_mysql/security/filtering/combined.py
fastmcp_mysql/security/filtering/whitelist.py
fastmcp_mysql/security/injection/__init__.py
fastmcp_mysql/security/injection/detector.py
fastmcp_mysql/security/injection/patterns.py
fastmcp_mysql/security/interfaces/__init__.py
fastmcp_mysql/security/interfaces/injection_detector.py
fastmcp_mysql/security/interfaces/query_filter.py
fastmcp_mysql/security/interfaces/rate_limiter.py
fastmcp_mysql/security/rate_limiting/__init__.py
fastmcp_mysql/security/rate_limiting/factory.py
fastmcp_mysql/security/rate_limiting/fixed_window.py
fastmcp_mysql/security/rate_limiting/sliding_window.py
fastmcp_mysql/security/rate_limiting/token_bucket.py
fastmcp_mysql/tools/__init__.py
fastmcp_mysql/tools/query.py
fastmcp_mysql-0.1.2.dist-info/METADATA
fastmcp_mysql-0.1.2.dist-info/WHEEL
fastmcp_mysql-0.1.2.dist-info/entry_points.txt
fastmcp_mysql-0.1.2.dist-info/licenses/LICENSE
fastmcp_mysql-0.1.2.dist-info/RECORD
