Metadata-Version: 2.4
Name: fastmcp-mysql
Version: 0.1.2
Summary: FastMCP server for MySQL database operations
Project-URL: Homepage, https://github.com/jinto/fastmcp-mysql
Project-URL: Bug Reports, https://github.com/jinto/fastmcp-mysql/issues
Project-URL: Source, https://github.com/jinto/fastmcp-mysql
Author-email: "박제권(Jae Kwon Park)" <jaypark@gmail.com>
License-Expression: MIT
License-File: LICENSE
Keywords: ai,database,fastmcp,llm,mcp,mysql
Classifier: Development Status :: 3 - Alpha
Classifier: Intended Audience :: Developers
Classifier: License :: OSI Approved :: MIT License
Classifier: Programming Language :: Python :: 3
Classifier: Programming Language :: Python :: 3.10
Classifier: Programming Language :: Python :: 3.11
Classifier: Programming Language :: Python :: 3.12
Requires-Python: >=3.10
Requires-Dist: aiomysql>=0.2.0
Requires-Dist: cachetools>=5.3.0
Requires-Dist: fastmcp>=0.1.0
Requires-Dist: numpy>=1.24.0
Requires-Dist: pydantic-settings>=2.0
Requires-Dist: pydantic>=2.0
Requires-Dist: python-dotenv>=1.0.0
Requires-Dist: sqlparse>=0.4.0
Provides-Extra: dev
Requires-Dist: black>=23.0; extra == 'dev'
Requires-Dist: mypy>=1.0; extra == 'dev'
Requires-Dist: pre-commit>=3.0; extra == 'dev'
Requires-Dist: pytest-asyncio>=0.21.0; extra == 'dev'
Requires-Dist: pytest-cov>=4.0; extra == 'dev'
Requires-Dist: pytest-mock>=3.10; extra == 'dev'
Requires-Dist: pytest>=7.0; extra == 'dev'
Requires-Dist: ruff>=0.1.0; extra == 'dev'
